[
    {
        "id": 1,
        "title": "Bombilla Pico de Loro - acero",
        "currentPrice": 13900,
        "oldPrice": 23167,
        "description": "Oferta especial en bombillas de acero",
        "image": "https://d22fxaf9t8d39k.cloudfront.net/18b89e7248b473dd9093f234b047e7af6c768d41c5e0ab7ee25ef98eeadc30fa19762.jpeg",
        "category": "bombillas"
    },
    {
        "id": 2,
        "title": "BOMBILLON RECTO DELUXE PICO REY",
        "currentPrice": 44900,
        "oldPrice": null,
        "description": "Bombillón de lujo con diseño Pico Rey",
        "image": "https://d22fxaf9t8d39k.cloudfront.net/46431e3719415945abae6f15090bf5c08774b0d6af013e3a7ab07b77cf16ad3c19762.jpg",
        "category": "bombillas"
    },
    {
        "id": 3,
        "title": "BOMBILLON  DELUXE",
        "currentPrice": 44900,
        "oldPrice": 54900,
        "description": "Bombillón de lujo con descuento especial",
        "image": "https://d22fxaf9t8d39k.cloudfront.net/191168ba71103fe4e990811e5a8c028a1c008b557951ad7a1c2c9b4195efe22f19762.jpg",
        "category": "bombillas"
    },
    {
        "id": 4,
        "title": "BOMBILLA STANLEY",
        "currentPrice": 44990,
        "oldPrice": null,
        "description": "Bombilla de alta calidad marca Stanley",
        "image": "https://d22fxaf9t8d39k.cloudfront.net/900263b8e2bb6e2a2946c4781bf5f46e2ba30cfa0fe4c9bf01f8f6804b910c1819762.jpg",
        "category": "bombillas"
    },
    {
        "id": 5,
        "title": "BOMBILLON PICO LORO DORADO LISO",
        "currentPrice": 42990,
        "oldPrice": 47767,
        "description": "Bombillón dorado liso con diseño Pico Loro",
        "image": "https://d22fxaf9t8d39k.cloudfront.net/52f803ec07d39749eda8d86b1fb69bc72ab54cb5672773f4e4aa23004d71db3219762.jpg",
        "category": "bombillas"
    },
    {
        "id": 6,
        "title": "BOMBILLA PICO REY LISO",
        "currentPrice": 34990,
        "oldPrice": 38990,
        "description": "Bombilla lisa con diseño Pico Rey",
        "image": "https://d22fxaf9t8d39k.cloudfront.net/8ea56716d8f65ef7e24c56f21c1937ec581caa9e33de662d737c90fe3c88376519762.png",
        "category": "bombillas"
    },
    {
        "id": 7,
        "title": "BOMBILLA PICO REY CINCELADA",
        "currentPrice": 34990,
        "oldPrice": 38990,
        "description": "Bombilla cincelada con diseño Pico Rey",
        "image": "https://d22fxaf9t8d39k.cloudfront.net/1ef79b101cbff0facbe9cac71bc24ec213c22dcf0031ce5451e58565b1b7bfea19762.png",
        "category": "bombillas"
    },
    {
        "id": 8,
        "title": "BOMBILLON PICO LORO COBRE",
        "currentPrice": 44990,
        "oldPrice": 49990,
        "description": "Bombillón de cobre con diseño Pico Loro",
        "image": "https://d22fxaf9t8d39k.cloudfront.net/41574823edef0d9fc560776d232296590eeeb3a14e16a472bda1990decdcf97119762.png",
        "category": "bombillas"
    },
    {
        "id": 9,
        "title": "BOMBILLA SEMI RECTA",
        "currentPrice": 34990,
        "oldPrice": 38990,
        "description": "Bombilla semi recta con descuento especial",
        "image": "https://d22fxaf9t8d39k.cloudfront.net/57f9c4e1661be617689607bc80b46e8c68d3b9611e4825689234e70de9ac558a19762.png",
        "category": "bombillas"
    },
    {
        "id": 10,
        "title": "BOMBILLON PICO REY",
        "currentPrice": 42990,
        "oldPrice": 46990,
        "description": "Bombillón con diseño Pico Rey",
        "image": "https://d22fxaf9t8d39k.cloudfront.net/547e838fee1358eef5a4a28a7f73f04126c8aef5cee46275e186f90e4e00d42c19762.png",
        "category": "bombillas"
    },
    {
        "id": 11,
        "title": "BOMBILLON PICO REY DORADO",
        "currentPrice": 42990,
        "oldPrice": 46990,
        "description": "Bombillón dorado con diseño Pico Rey",
        "image": "https://d22fxaf9t8d39k.cloudfront.net/4fa2dfeba8206fd2d985734efd128118865bd8248a960332f6e6f3e484eef44719762.png",
        "category": "bombillas"
    },
    {
        "id": 12,
        "title": "BOMBILLON PICO LORO DORADO",
        "currentPrice": 34990,
        "oldPrice": 38990,
        "description": "Bombillón dorado con diseño Pico Loro",
        "image": "https://d22fxaf9t8d39k.cloudfront.net/86d07d754b03c7f028f9b2b78eccbbf1be619867f1cc498a4dec10bf6679b81219762.png",
        "category": "bombillas"
    },
    {
        "id": 13,
        "title": "BOMBILLON PICO LORO",
        "currentPrice": 42990,
        "oldPrice": 46990,
        "description": "Bombillón con diseño Pico Loro",
        "image": "https://d22fxaf9t8d39k.cloudfront.net/8be03d1fab57eedec4910787456d447061715dddf031d48841d28c810aacef0519762.png",
        "category": "bombillas"
    },
    {
        "id": 14,
        "title": "BOMBILLA SEMI RECTA CON VIROLA",
        "currentPrice": 34990,
        "oldPrice": 38990,
        "description": "Bombilla semi recta con virola",
        "image": "https://d22fxaf9t8d39k.cloudfront.net/bdfbe3dc6f238b555c772dcc7989b98a243d951f9e1a9ac074105d16d205804a19762.png",
        "category": "bombillas"
    },
    {
        "id": 15,
        "title": "BOMBILLA PICO LORO DESARMABLE",
        "currentPrice": 55990,
        "oldPrice": 61990,
        "description": "Bombilla desarmable con diseño Pico Loro",
        "image": "https://d22fxaf9t8d39k.cloudfront.net/2a8c104bc9e6a84893533bbe6e1093195a9c748489aeb801c007960d205f24d319762.png",
        "category": "bombillas"
    },
    {
        "id": 16,
        "title": "BOMBILLA PICO LORO LISA",
        "currentPrice": 34990,
        "oldPrice": 38990,
        "description": "Bombilla lisa con diseño Pico Loro",
        "image": "https://d22fxaf9t8d39k.cloudfront.net/6359a1f5afa39aaa9a3a0cbf5b963dafa352e6687464d1d3203f433471655f1319762.jpg",
        "category": "bombillas"
    },
    {
        "id": 17,
        "title": "BOMBILLON NIQUELADO",
        "currentPrice": 33990,
        "oldPrice": 37990,
        "description": "Bombillón niquelado con descuento especial",
        "image": "https://d22fxaf9t8d39k.cloudfront.net/9031744d97fac21765a132c2be3bfe5ba25674a1136a6d12742018f61be3612519762.png",
        "category": "bombillas"
    },
    {
        "id": 18,
        "title": "BOMBILLA SEMI RECTA NIQUELADA",
        "currentPrice": 19990,
        "oldPrice": 22990,
        "description": "Bombilla semi recta niquelada",
        "image": "https://d22fxaf9t8d39k.cloudfront.net/23f0ea0ffbdb774f8063e72a280d0a4349b14a19bfb3cf9b90f2caff8a94e0bc19762.png",
        "category": "bombillas"
    },
    {
        "id": 19,
        "title": "Bombilla Pico loro Cincelada - acero",
        "currentPrice": 13990,
        "oldPrice": 15990,
        "description": "Bombilla cincelada de acero con diseño Pico Loro",
        "image": "https://d22fxaf9t8d39k.cloudfront.net/faa9b36ec0880e357612578d0f46cbaa1696f3ce817498d8207e02f7f69924b519762.jpg",
        "category": "bombillas"
    },
    {
        "id": 20,
        "title": "BOMBILLON de Alpaca CINCELADO",
        "currentPrice": 36990,
        "oldPrice": 40990,
        "description": "Bombillón de alpaca cincelado",
        "image": "https://d22fxaf9t8d39k.cloudfront.net/918a2b36150c254c706c683877d5e3e2efe03a9ff42611cf5e3fbc91355d629519762.jpeg",
        "category": "bombillas"
    },
    {
        "id": 21,
        "title": "BOMBILLÓN Pico de Rey Alpaca",
        "currentPrice": 31990,
        "oldPrice": 34990,
        "description": "Bombillón de alpaca con diseño Pico Rey",
        "image": "https://d22fxaf9t8d39k.cloudfront.net/c15629afbc5e55f93497dda4496c42b3539a6e9bc4fe581f8a8bc43d9cd9c7b819762.jpeg",
        "category": "bombillas"
    }
]